typetowritescreen/__init__.py
typetowritescreen/contentnavigationdrawer.py
typetowritescreen/navigationlayout.py
typetowritescreen/nulis.py
typetowritescreen/screen1.kv
typetowritescreen/screen1.py
typetowritescreen/screen2.kv
typetowritescreen/screen2.py
typetowritescreen/typetowritescreen.kv
typetowritescreen/typetowritescreen.py
typetowritescreen-0.0.9.dist-info/LICENSE
typetowritescreen-0.0.9.dist-info/METADATA
typetowritescreen-0.0.9.dist-info/WHEEL
typetowritescreen-0.0.9.dist-info/top_level.txt
typetowritescreen-0.0.9.dist-info/RECORD
