Metadata-Version: 2.1
Name: typetowritescreen
Version: 0.0.9
Summary: Type To Write API that may help you easier to make a writing apps without making it from scratch
Home-page: https://github.com/will702/typetowritescreen
Author: Greg(GREGORIUS WILLSON)
Author-email: willson2016pos@gmail.com
License: MIT
Keywords: python,writing,writing api,writing gui,kivygui,writing kivy
Platform: UNKNOWN
Classifier: Development Status :: 1 - Planning
Classifier: Intended Audience :: Developers
Classifier: Programming Language :: Python :: 3
Classifier: Operating System :: Unix
Classifier: Operating System :: MacOS :: MacOS X
Classifier: Operating System :: Microsoft :: Windows
Requires-Dist: kivy
Requires-Dist: kivymd
Requires-Dist: gingerit
Requires-Dist: pillow
